[
  {"sentence": "I did not go to school yesterday.", "translation": "No fui a la escuela ayer."},
  {"sentence": "She did not like the movie.", "translation": "A ella no le gustó la película."},
  {"sentence": "He was not at home.", "translation": "Él no estaba en casa."},
  {"sentence": "We were not ready.", "translation": "No estábamos listos."},
  {"sentence": "They did not call me.", "translation": "No me llamaron."},
  {"sentence": "I will not go tomorrow.", "translation": "No iré mañana."},
  {"sentence": "She will not eat that.", "translation": "Ella no comerá eso."},
  {"sentence": "He will not come with us.", "translation": "Él no vendrá con nosotros."},
  {"sentence": "We cannot find it.", "translation": "No podemos encontrarlo."},
  {"sentence": "They cannot swim.", "translation": "Ellos no saben nadar."},

  {"sentence": "I do not understand this problem.", "translation": "No entiendo este problema."},
  {"sentence": "She does not work here anymore.", "translation": "Ella ya no trabaja aquí."},
  {"sentence": "He does not like coffee.", "translation": "A él no le gusta el café."},
  {"sentence": "We do not agree with that decision.", "translation": "No estamos de acuerdo con esa decisión."},
  {"sentence": "They do not know the answer.", "translation": "Ellos no saben la respuesta."},
  {"sentence": "I am not feeling well today.", "translation": "No me siento bien hoy."},
  {"sentence": "She is not coming tonight.", "translation": "Ella no viene esta noche."},
  {"sentence": "He is not interested.", "translation": "Él no está interesado."},
  {"sentence": "We are not tired yet.", "translation": "Todavía no estamos cansados."},
  {"sentence": "They are not listening.", "translation": "No están escuchando."},

  {"sentence": "I did not see him yesterday.", "translation": "No lo vi ayer."},
  {"sentence": "She did not finish her homework.", "translation": "Ella no terminó su tarea."},
  {"sentence": "He did not buy a new car.", "translation": "Él no compró un carro nuevo."},
  {"sentence": "We did not watch that movie.", "translation": "No vimos esa película."},
  {"sentence": "They did not visit their grandparents.", "translation": "No visitaron a sus abuelos."},
  {"sentence": "I will not forget this.", "translation": "No olvidaré esto."},
  {"sentence": "She will not be late.", "translation": "Ella no llegará tarde."},
  {"sentence": "He will not accept that.", "translation": "Él no aceptará eso."},
  {"sentence": "We will not stop now.", "translation": "No nos detendremos ahora."},
  {"sentence": "They will not agree.", "translation": "Ellos no estarán de acuerdo."},

  {"sentence": "I cannot believe it.", "translation": "No puedo creerlo."},
  {"sentence": "She cannot come today.", "translation": "Ella no puede venir hoy."},
  {"sentence": "He cannot speak Spanish.", "translation": "Él no sabe hablar español."},
  {"sentence": "We cannot leave yet.", "translation": "Todavía no podemos irnos."},
  {"sentence": "They cannot answer the question.", "translation": "No pueden responder la pregunta."},
  {"sentence": "I do not want to go.", "translation": "No quiero ir."},
  {"sentence": "She does not understand me.", "translation": "Ella no me entiende."},
  {"sentence": "He does not like this song.", "translation": "A él no le gusta esta canción."},
  {"sentence": "We do not need that now.", "translation": "No necesitamos eso ahora."},
  {"sentence": "They do not live here anymore.", "translation": "Ellos ya no viven aquí."},

  {"sentence": "I am not going to do it.", "translation": "No lo voy a hacer."},
  {"sentence": "She is not going to study today.", "translation": "Ella no va a estudiar hoy."},
  {"sentence": "He is not going to call you.", "translation": "Él no te va a llamar."},
  {"sentence": "We are not going to wait.", "translation": "No vamos a esperar."},
  {"sentence": "They are not going to join us.", "translation": "No se van a unir a nosotros."},
  {"sentence": "I did not want to hurt you.", "translation": "No quería lastimarte."},
  {"sentence": "She did not mean it.", "translation": "Ella no lo dijo en serio."},
  {"sentence": "He did not see the message.", "translation": "Él no vio el mensaje."},
  {"sentence": "We did not hear the alarm.", "translation": "No escuchamos la alarma."},
  {"sentence": "They did not recognize me.", "translation": "No me reconocieron."}
]
